githubauthlib/__init__.py
githubauthlib/github_auth.py
githubauthlib-2.0.1.dist-info/licenses/LICENSE
tests/__init__.py
tests/test_github_auth.py
githubauthlib-2.0.1.dist-info/METADATA
githubauthlib-2.0.1.dist-info/WHEEL
githubauthlib-2.0.1.dist-info/top_level.txt
githubauthlib-2.0.1.dist-info/RECORD
